Metadata-Version: 1.0
Name: NSI-Bertrand
Version: 0.5.1
Summary: Fonctions et outils pour la NSI
Home-page: UNKNOWN
Author: Benjamin Bertrand
Author-email: benjamin.bertrand@ac-lyon.fr
License: UNKNOWN
Platform: UNKNOWN
